myo_gestures/__init__.py
myo_gestures/common.py
myo_gestures/data_loader.py
myo_gestures/myo_feat_extract.py
myo_gestures/myo_raw.py
myo_gestures/pnn_train.py
myo_gestures/real_time.py
myo_gestures/semg_network.py
myo_gestures/train_net.py
myo_gestures/transfer_learn.py
myo_gestures-0.0.8.data/scripts/data_loader.py
myo_gestures-0.0.8.data/scripts/real_time.py
myo_gestures-0.0.8.data/scripts/train_net.py
myo_gestures-0.0.8.data/scripts/transfer_learn.py
myo_gestures-0.0.8.dist-info/LICENSE
myo_gestures-0.0.8.dist-info/METADATA
myo_gestures-0.0.8.dist-info/WHEEL
myo_gestures-0.0.8.dist-info/top_level.txt
myo_gestures-0.0.8.dist-info/RECORD
